{"seeds": [{"seed": 23, "data": {"fs": [{"f": "\\sqrt[7]{p^3}", "fn": "G", "x": "p", "df": "\\frac{3}{7 \\, p^{\\frac{4}{7}}}"}, {"f": "2 \\, w^{4} + 4 \\, e^{w} - 4", "fn": "h", "x": "w", "df": "8 \\, w^{3} + 4 \\, e^{w}"}, {"f": "\\frac{4}{y^{5}}", "fn": "f", "x": "y", "df": "-\\frac{20}{y^{6}}"}, {"f": "6 \\, y^{6} - 3 \\, y^{2} - y + 4", "fn": "h", "x": "y", "df": "36 \\, y^{5} - 6 \\, y - 1"}, {"f": "3 \\, q^{\\frac{7}{4}} - 2 \\, q^{\\frac{3}{4}}", "fn": "h", "x": "q", "df": "\\frac{21}{4} \\, q^{\\frac{3}{4}} - \\frac{3}{2 \\, q^{\\frac{1}{4}}}"}], "__seed__": "0023"}}, {"seed": 748, "data": {"fs": [{"f": "\\frac{2}{r^{2}}", "fn": "g", "x": "r", "df": "-\\frac{4}{r^{3}}"}, {"f": "4 \\, x^{\\frac{5}{3}} - 3 \\, x^{\\frac{2}{3}}", "fn": "G", "x": "x", "df": "\\frac{20}{3} \\, x^{\\frac{2}{3}} - \\frac{2}{x^{\\frac{1}{3}}}"}, {"f": "8 \\, x^{4} - 2 \\, x^{3} - 8 \\, x^{2} + 4", "fn": "f", "x": "x", "df": "32 \\, x^{3} - 6 \\, x^{2} - 16 \\, x"}, {"f": "-w^{3} + e^{w} + 2", "fn": "G", "x": "w", "df": "-3 \\, w^{2} + e^{w}"}, {"f": "\\sqrt[7]{r^5}", "fn": "h", "x": "r", "df": "\\frac{5}{7 \\, r^{\\frac{2}{7}}}"}], "__seed__": "0748"}}, {"seed": 358, "data": {"fs": [{"f": "\\sqrt[3]{v^4}", "fn": "g", "x": "v", "df": "\\frac{4}{3} \\, v^{\\frac{1}{3}}"}, {"f": "4 \\, y^{5} + 5 \\, y^{4} + 3 \\, y^{3} - 1", "fn": "j", "x": "y", "df": "20 \\, y^{4} + 20 \\, y^{3} + 9 \\, y^{2}"}, {"f": "2 \\, r^{\\frac{5}{3}} - 2 \\, r^{\\frac{2}{3}}", "fn": "f", "x": "r", "df": "\\frac{10}{3} \\, r^{\\frac{2}{3}} - \\frac{4}{3 \\, r^{\\frac{1}{3}}}"}, {"f": "-\\frac{1}{w^{3}}", "fn": "R", "x": "w", "df": "\\frac{3}{w^{4}}"}, {"f": "2 \\, t^{4} + e^{t} + 4", "fn": "F", "x": "t", "df": "8 \\, t^{3} + e^{t}"}], "__seed__": "0358"}}, {"seed": 215, "data": {"fs": [{"f": "\\sqrt[7]{q^5}", "fn": "R", "x": "q", "df": "\\frac{5}{7 \\, q^{\\frac{2}{7}}}"}, {"f": "-4 \\, y^{3} - 4 \\, e^{y} - 3", "fn": "G", "x": "y", "df": "-12 \\, y^{2} - 4 \\, e^{y}"}, {"f": "\\frac{1}{t^{5}}", "fn": "F", "x": "t", "df": "-\\frac{5}{t^{6}}"}, {"f": "3 \\, p^{\\frac{7}{4}} - 2 \\, p^{\\frac{3}{4}}", "fn": "f", "x": "p", "df": "\\frac{21}{4} \\, p^{\\frac{3}{4}} - \\frac{3}{2 \\, p^{\\frac{1}{4}}}"}, {"f": "7 \\, r^{6} + 7 \\, r^{5} - 9 \\, r + 4", "fn": "F", "x": "r", "df": "42 \\, r^{5} + 35 \\, r^{4} - 9"}], "__seed__": "0215"}}, {"seed": 409, "data": {"fs": [{"f": "\\frac{2}{x^{5}}", "fn": "R", "x": "x", "df": "-\\frac{10}{x^{6}}"}, {"f": "3 \\, t^{\\frac{7}{4}} - 4 \\, t^{\\frac{3}{4}}", "fn": "g", "x": "t", "df": "\\frac{21}{4} \\, t^{\\frac{3}{4}} - \\frac{3}{t^{\\frac{1}{4}}}"}, {"f": "\\sqrt[3]{y^4}", "fn": "h", "x": "y", "df": "\\frac{4}{3} \\, y^{\\frac{1}{3}}"}, {"f": "7 \\, u^{6} + 5 \\, u^{3} - 9 \\, u + 7", "fn": "f", "x": "u", "df": "42 \\, u^{5} + 15 \\, u^{2} - 9"}, {"f": "-4 \\, x^{3} - e^{x} - 2", "fn": "H", "x": "x", "df": "-12 \\, x^{2} - e^{x}"}], "__seed__": "0409"}}, {"seed": 198, "data": {"fs": [{"f": "-2 \\, p^{2} + 4 \\, e^{p} - 4", "fn": "j", "x": "p", "df": "-4 \\, p + 4 \\, e^{p}"}, {"f": "\\frac{1}{t^{2}}", "fn": "H", "x": "t", "df": "-\\frac{2}{t^{3}}"}, {"f": "2 \\, y^{\\frac{5}{3}} - 4 \\, y^{\\frac{2}{3}}", "fn": "G", "x": "y", "df": "\\frac{10}{3} \\, y^{\\frac{2}{3}} - \\frac{8}{3 \\, y^{\\frac{1}{3}}}"}, {"f": "\\sqrt[4]{y^5}", "fn": "G", "x": "y", "df": "\\frac{5}{4} \\, y^{\\frac{1}{4}}"}, {"f": "-5 \\, x^{6} + 3 \\, x^{5} + 2 \\, x^{2} + 7", "fn": "f", "x": "x", "df": "-30 \\, x^{5} + 15 \\, x^{4} + 4 \\, x"}], "__seed__": "0198"}}, {"seed": 721, "data": {"fs": [{"f": "\\frac{2}{x^{4}}", "fn": "R", "x": "x", "df": "-\\frac{8}{x^{5}}"}, {"f": "-4 \\, t^{4} + 3 \\, e^{t} - 4", "fn": "h", "x": "t", "df": "-16 \\, t^{3} + 3 \\, e^{t}"}, {"f": "2 \\, v^{\\frac{7}{4}} - 4 \\, v^{\\frac{3}{4}}", "fn": "R", "x": "v", "df": "\\frac{7}{2} \\, v^{\\frac{3}{4}} - \\frac{3}{v^{\\frac{1}{4}}}"}, {"f": "\\sqrt[7]{p^3}", "fn": "f", "x": "p", "df": "\\frac{3}{7 \\, p^{\\frac{4}{7}}}"}, {"f": "7 \\, t^{5} - 5 \\, t^{3} - 5 \\, t - 6", "fn": "f", "x": "t", "df": "35 \\, t^{4} - 15 \\, t^{2} - 5"}], "__seed__": "0721"}}, {"seed": 191, "data": {"fs": [{"f": "v^{4} - 2 \\, e^{v} + 2", "fn": "f", "x": "v", "df": "4 \\, v^{3} - 2 \\, e^{v}"}, {"f": "-\\frac{1}{p^{3}}", "fn": "f", "x": "p", "df": "\\frac{3}{p^{4}}"}, {"f": "\\sqrt[3]{x^7}", "fn": "H", "x": "x", "df": "\\frac{7}{3} \\, x^{\\frac{4}{3}}"}, {"f": "4 \\, v^{\\frac{5}{3}} - 3 \\, v^{\\frac{2}{3}}", "fn": "g", "x": "v", "df": "\\frac{20}{3} \\, v^{\\frac{2}{3}} - \\frac{2}{v^{\\frac{1}{3}}}"}, {"f": "2 \\, w^{3} + 8 \\, w^{2} + w - 8", "fn": "j", "x": "w", "df": "6 \\, w^{2} + 16 \\, w + 1"}], "__seed__": "0191"}}, {"seed": 627, "data": {"fs": [{"f": "2 \\, y^{\\frac{7}{4}} - 4 \\, y^{\\frac{3}{4}}", "fn": "S", "x": "y", "df": "\\frac{7}{2} \\, y^{\\frac{3}{4}} - \\frac{3}{y^{\\frac{1}{4}}}"}, {"f": "\\sqrt[4]{x^5}", "fn": "h", "x": "x", "df": "\\frac{5}{4} \\, x^{\\frac{1}{4}}"}, {"f": "\\frac{4}{w^{5}}", "fn": "f", "x": "w", "df": "-\\frac{20}{w^{6}}"}, {"f": "-q^{6} - 9 \\, q^{3} + 5 \\, q^{2} + 3", "fn": "S", "x": "q", "df": "-6 \\, q^{5} - 27 \\, q^{2} + 10 \\, q"}, {"f": "-w^{3} + e^{w} - 2", "fn": "H", "x": "w", "df": "-3 \\, w^{2} + e^{w}"}], "__seed__": "0627"}}, {"seed": 775, "data": {"fs": [{"f": "\\sqrt[5]{y^3}", "fn": "F", "x": "y", "df": "\\frac{3}{5 \\, y^{\\frac{2}{5}}}"}, {"f": "\\frac{3}{p^{5}}", "fn": "j", "x": "p", "df": "-\\frac{15}{p^{6}}"}, {"f": "3 \\, x^{\\frac{5}{3}} - 2 \\, x^{\\frac{2}{3}}", "fn": "S", "x": "x", "df": "5 \\, x^{\\frac{2}{3}} - \\frac{4}{3 \\, x^{\\frac{1}{3}}}"}, {"f": "y^{3} - 2 \\, e^{y} + 4", "fn": "R", "x": "y", "df": "3 \\, y^{2} - 2 \\, e^{y}"}, {"f": "-5 \\, w^{5} - 6 \\, w^{4} + 8 \\, w - 5", "fn": "R", "x": "w", "df": "-25 \\, w^{4} - 24 \\, w^{3} + 8"}], "__seed__": "0775"}}], "generated_on": "2024-09-29T18:44:05.471377+00:00"}